cppman/__init__.py
cppman/__version__.py
cppman/config.py
cppman/crawler.py
cppman/environ.py
cppman/main.py
cppman/util.py
cppman/__pycache__/__init__.cpython-314.opt-2.pyc
cppman/__pycache__/__version__.cpython-314.opt-2.pyc
cppman/__pycache__/config.cpython-314.opt-2.pyc
cppman/__pycache__/crawler.cpython-314.opt-2.pyc
cppman/__pycache__/environ.cpython-314.opt-2.pyc
cppman/__pycache__/main.cpython-314.opt-2.pyc
cppman/__pycache__/util.cpython-314.opt-2.pyc
cppman/formatter/__init__.py
cppman/formatter/cplusplus.py
cppman/formatter/cppreference.py
cppman/formatter/tableparser.py
cppman/formatter/__pycache__/__init__.cpython-314.opt-2.pyc
cppman/formatter/__pycache__/cplusplus.cpython-314.opt-2.pyc
cppman/formatter/__pycache__/cppreference.cpython-314.opt-2.pyc
cppman/formatter/__pycache__/tableparser.cpython-314.opt-2.pyc
cppman/lib/cppman.vim
cppman/lib/index.db
cppman/lib/pager.sh
cppman-0.6.0.data/data/share/bash-completion/completions/cppman.bash
cppman-0.6.0.data/data/share/doc/cppman/AUTHORS
cppman-0.6.0.data/data/share/doc/cppman/COPYING
cppman-0.6.0.data/data/share/doc/cppman/ChangeLog
cppman-0.6.0.data/data/share/doc/cppman/README.rst
cppman-0.6.0.data/data/share/fish/vendor_completions.d/cppman.fish
cppman-0.6.0.data/data/share/man/man1/cppman.1
cppman-0.6.0.data/data/share/zsh/vendor-completions/_cppman
cppman-0.6.0.data/scripts/cppman
cppman-0.6.0.dist-info/licenses/AUTHORS
cppman-0.6.0.dist-info/licenses/COPYING
cppman-0.6.0.dist-info/METADATA
cppman-0.6.0.dist-info/WHEEL
cppman-0.6.0.dist-info/top_level.txt
cppman-0.6.0.dist-info/RECORD
