Metadata-Version: 2.4
Name: cppman
Version: 0.6.0
Summary: C++ 98/11/14/17/20 manual pages for Linux/MacOS
Home-page: https://github.com/aitjcize/cppman
Author: Wei-Ning Huang (AZ)
Author-email: aitjcize@gmail.com
License: GPL
Classifier: Programming Language :: Python :: 3.5
Classifier: Programming Language :: Python :: 3.6
Classifier: Programming Language :: Python :: 3.7
Classifier: Programming Language :: Python :: 3.8
Classifier: Programming Language :: Python :: 3 :: Only
Classifier: Topic :: Software Development :: Documentation
License-File: COPYING
License-File: AUTHORS
Requires-Dist: beautifulsoup4==4.13.3
Requires-Dist: bs4==0.0.2
Requires-Dist: html5lib==1.1
Requires-Dist: lxml==5.3.2
Requires-Dist: six==1.17.0
Requires-Dist: soupsieve==2.6
Requires-Dist: typing_extensions==4.13.1
Requires-Dist: webencodings==0.5.1
Dynamic: author
Dynamic: author-email
Dynamic: classifier
Dynamic: home-page
Dynamic: license
Dynamic: license-file
Dynamic: requires-dist
Dynamic: summary
